xnat4tests/__init__.py
xnat4tests/_version.py
xnat4tests/base.py
xnat4tests/cli.py
xnat4tests/config.py
xnat4tests/data.py
xnat4tests/registry.py
xnat4tests/testing.py
xnat4tests/utils.py
xnat4tests/docker-src/Dockerfile
xnat4tests/docker-src/XNAT.sql
xnat4tests/docker-src/launch-xnat.sh
xnat4tests/docker-src/make-xnat-config.sh
xnat4tests/docker-src/postfix-start
xnat4tests/docker-src/supervisord.conf
xnat4tests/docker-src/xnat-prefs-init.ini
xnat4tests-0.4.1.dist-info/licenses/LICENSE
xnat4tests-0.4.1.dist-info/METADATA
xnat4tests-0.4.1.dist-info/WHEEL
xnat4tests-0.4.1.dist-info/entry_points.txt
xnat4tests-0.4.1.dist-info/top_level.txt
xnat4tests-0.4.1.dist-info/RECORD
