Metadata-Version: 2.4
Name: xnat4tests
Version: 0.4.1
Summary: Creates basic XNAT instance for API tests
Home-page: https://github.com/australian-imaging-service/xnat4tests
Author: Thomas G. Close
Author-email: tom.g.close@gmail.com
License: Apache License 2.0
Keywords: repository analysis neuroimaging workflows pipelines
Classifier: Development Status :: 4 - Beta
Classifier: Intended Audience :: Healthcare Industry
Classifier: Intended Audience :: Science/Research
Classifier: License :: OSI Approved :: Apache Software License
Classifier: Natural Language :: English
Classifier: Topic :: Scientific/Engineering :: Bio-Informatics
Classifier: Topic :: Scientific/Engineering :: Medical Science Apps.
Classifier: Programming Language :: Python :: 3.7
Classifier: Programming Language :: Python :: 3.8
Classifier: Programming Language :: Python :: 3.9
Classifier: Programming Language :: Python :: 3.10
License-File: LICENSE
Requires-Dist: docker>=5.0.2
Requires-Dist: xnat
Requires-Dist: click>=7.1.2
Requires-Dist: requests>=2.10.0
Requires-Dist: medimages4tests>=0.3
Requires-Dist: PyYAML>=6.0
Provides-Extra: test
Requires-Dist: pytest>=5.4.3; extra == "test"
Requires-Dist: pytest-cov>=2.12.1; extra == "test"
Dynamic: author
Dynamic: author-email
Dynamic: classifier
Dynamic: description
Dynamic: home-page
Dynamic: keywords
Dynamic: license
Dynamic: license-file
Dynamic: provides-extra
Dynamic: requires-dist
Dynamic: summary
